commandor/__init__.py
commandor/main.py
commandor/terminal.py
commandor_ai-1.0.2.dist-info/licenses/LICENSE
commandor_ai-1.0.2.dist-info/METADATA
commandor_ai-1.0.2.dist-info/WHEEL
commandor_ai-1.0.2.dist-info/entry_points.txt
commandor_ai-1.0.2.dist-info/top_level.txt
commandor_ai-1.0.2.dist-info/RECORD
