Metadata-Version: 2.4
Name: commandor-ai
Version: 1.0.2
Summary: An intelligent terminal assistant that uses AI to convert natural language to shell commands
Home-page: https://github.com/ravin-d-27/Commandor
Author: Ravin D
Author-email: Ravin D <ravin.d3107@outlook.com>
License: Proprietary
Project-URL: Homepage, https://github.com/ravin-d-27/Commandor
Project-URL: BugReports, https://github.com/ravin-d-27/Commandor/issues
Project-URL: Source, https://github.com/ravin-d-27/Commandor
Project-URL: Documentation, https://github.com/ravin-d-27/Commandor#readme
Keywords: terminal,ai,shell,command-line,natural-language,gemini,assistant,automation,cli,productivity
Classifier: Development Status :: 4 - Beta
Classifier: Intended Audience :: Developers
Classifier: Intended Audience :: System Administrators
Classifier: License :: Free for non-commercial use
Classifier: Operating System :: OS Independent
Classifier: Programming Language :: Python :: 3
Classifier: Programming Language :: Python :: 3.7
Classifier: Programming Language :: Python :: 3.8
Classifier: Programming Language :: Python :: 3.9
Classifier: Programming Language :: Python :: 3.10
Classifier: Programming Language :: Python :: 3.11
Classifier: Programming Language :: Python :: 3.12
Classifier: Topic :: Software Development :: Libraries :: Python Modules
Classifier: Topic :: System :: Shells
Classifier: Topic :: System :: System Shells
Classifier: Topic :: Terminals
Classifier: Topic :: Utilities
Requires-Python: >=3.7
License-File: LICENSE
Requires-Dist: google-generativeai>=0.3.0
Requires-Dist: python-decouple>=3.6
Requires-Dist: colorama>=0.4.4
Provides-Extra: windows
Requires-Dist: pyreadline3>=3.4.1; extra == "windows"
Dynamic: author
Dynamic: home-page
Dynamic: license-file
Dynamic: requires-python
